{"namedChunkGroups":{"polyfill":{"name":"polyfill","assets":[{"name":"webpack-runtime-0420f3ce204cf248ed88.js","size":4282},{"name":"polyfill-adf437c7f8308d493997.js","size":84323}],"filteredAssets":0,"assetsSize":88605,"filteredAuxiliaryAssets":2,"auxiliaryAssetsSize":223039},"app":{"name":"app","assets":[{"name":"webpack-runtime-0420f3ce204cf248ed88.js","size":4282},{"name":"framework-35399193a0a650e2f200.js","size":128880},{"name":"app-c9194b9d6903799f39f4.js","size":49791}],"filteredAssets":0,"assetsSize":182953,"filteredAuxiliaryAssets":3,"auxiliaryAssetsSize":545997},"component---src-pages-404-js":{"name":"component---src-pages-404-js","assets":[{"name":"component---src-pages-404-js-da19968e4b00979f9461.js","size":810}],"filteredAssets":0,"assetsSize":810,"filteredAuxiliaryAssets":1,"auxiliaryAssetsSize":1980},"component---src-pages-index-js":{"name":"component---src-pages-index-js","assets":[{"name":"styles.65be50aec78c4cbb09e0.css","size":298},{"name":"component---src-pages-index-js-cf41d073b66bba56638b.js","size":14485}],"filteredAssets":0,"assetsSize":14783,"filteredAuxiliaryAssets":1,"auxiliaryAssetsSize":64144}},"assetsByChunkName":{"polyfill":["webpack-runtime-0420f3ce204cf248ed88.js","polyfill-adf437c7f8308d493997.js"],"app":["webpack-runtime-0420f3ce204cf248ed88.js","framework-35399193a0a650e2f200.js","app-c9194b9d6903799f39f4.js"],"component---src-pages-404-js":["component---src-pages-404-js-da19968e4b00979f9461.js"],"component---src-pages-index-js":["styles.65be50aec78c4cbb09e0.css","component---src-pages-index-js-cf41d073b66bba56638b.js"]},"childAssetsByChunkName":{}}